{"is_source_file": true, "format": "JavaScript/JSX", "description": "React component Header that displays branding and a search input for filtering recipes in a recipe exploration app.", "external_files": ["react", "react-router-dom", "../context/RecipesContext"], "external_methods": ["useRecipes"], "published": ["Header"], "classes": [], "methods": [{"name": "Header()", "description": "React functional component that renders the header with brand info and search input.", "scope": "", "scopeKind": ""}], "calls": ["useRecipes()", "setQuery", "Link"], "search-terms": ["Header", "React component", "search bar", "recipe explorer", "brand logo", "filter recipes", "sign-in link"], "state": 2, "file_id": 17, "knowledge_revision": 55, "git_revision": "2486c73c79087bd205f08375550616b6e411ec30", "revision_history": [{"41": ""}, {"55": "2486c73c79087bd205f08375550616b6e411ec30"}], "ctags": [{"_type": "tag", "name": "Header", "path": "/home/kavia/workspace/code-generation/recipe-explorer-183464-183507/frontend_ui/src/components/Header.jsx", "pattern": "/^function Header() {$/", "language": "JavaScript", "kind": "function", "signature": "()"}, {"_type": "tag", "name": "query", "path": "/home/kavia/workspace/code-generation/recipe-explorer-183464-183507/frontend_ui/src/components/Header.jsx", "pattern": "/^          value={query}$/", "language": "JavaScript", "kind": "field", "scope": "Header.value", "scopeKind": "class"}], "hash": "70f694bf921151213cb813a515e9f82b", "format-version": 4, "code-base-name": "frontend_ui", "filename": "frontend_ui/src/components/Header.jsx", "fields": [{"name": "value={query}", "scope": "Header.value", "scopeKind": "class", "description": "unavailable"}]}